MANIFEST.in
setup.py
sensor_outlier_detector/__init__.py
sensor_outlier_detector/add.py
sensor_outlier_detector/subtract.py
sensor_outlier_detector.egg-info/PKG-INFO
sensor_outlier_detector.egg-info/SOURCES.txt
sensor_outlier_detector.egg-info/dependency_links.txt
sensor_outlier_detector.egg-info/not-zip-safe
sensor_outlier_detector.egg-info/top_level.txt
sensor_outlier_detector/adv/__init__.py
sensor_outlier_detector/adv/__init__.pyc
sensor_outlier_detector/adv/fib.py
sensor_outlier_detector/adv/fib.pyc
sensor_outlier_detector/adv/sqrt.py
sensor_outlier_detector/adv/sqrt.pyc