Metadata-Version: 1.0
Name: sensor-outlier-detector
Version: 0.3
Summary: sensor data outlier in the world
Home-page: http://github.com/vijayendra-g/sensor_outlier_detector
Author: vijay G
Author-email: vijayendra.iiith@gmail.com
License: GNU
Platform: UNKNOWN
